{
"type": "FeatureCollection",
"features": [
{
  "type": "Feature",
  "id": "way/307484459",
  "properties": {
    "addr:city": "Garoua",
    "amenity": "university",
    "name": "Institut Superieur Yerima Dewa",
    "id": "way/307484459"
  },
  "geometry": {
    "type": "Point",
    "coordinates": [
      13.3849548,
      9.3597761
    ]
  }
}
]
}
