{
"type": "FeatureCollection",
"features": [
{
  "type": "Feature",
  "id": "way/251369723",
  "properties": {
    "addr:city": "Libreville",
    "addr:housenumber": "680",
    "addr:postcode": "BP13131",
    "addr:street": "Boulevard du Président Léon M'ba",
    "amenity": "university",
    "name": "Université Omar Bongo",
    "name:en": "Omar Bongo University",
    "old_name": "Université nationale du Gabon",
    "old_name:en": "National University of Gabon",
    "ref": "Universite Omar Bongo Ondimba",
    "website": "http://www.uob.ga/",
    "wikidata": "Q3551470",
    "wikipedia": "en:Omar Bongo University",
    "id": "way/251369723"
  },
  "geometry": {
    "type": "Point",
    "coordinates": [
      9.4452503,
      0.4185627
    ]
  }
},
{
  "type": "Feature",
  "id": "node/4752937914",
  "properties": {
    "amenity": "university",
    "name": "Campus UOB",
    "id": "node/4752937914"
  },
  "geometry": {
    "type": "Point",
    "coordinates": [
      9.4435292,
      0.4179229
    ]
  }
}
]
}
