{
"type": "FeatureCollection",
"features": [
{
  "type": "Feature",
  "id": "way/332260292",
  "properties": {
    "amenity": "hospital",
    "name": "Centre médico-social",
    "id": "way/332260292"
  },
  "geometry": {
    "type": "Point",
    "coordinates": [
      13.5487829,
      7.4159543
    ]
  }
},
{
  "type": "Feature",
  "id": "node/4391694825",
  "properties": {
    "amenity": "hospital",
    "name": "Hôpital régional de Ngaoundéré",
    "id": "node/4391694825"
  },
  "geometry": {
    "type": "Point",
    "coordinates": [
      13.584119,
      7.3151335
    ]
  }
},
{
  "type": "Feature",
  "id": "node/4453234586",
  "properties": {
    "amenity": "hospital",
    "name": "Protestant Hospital of Ngaoundéré",
    "operator": "EELC",
    "url": "http://www.oseelc.org/",
    "wikidata": "Q7251608",
    "wikipedia": "en:Protestant Hospital of Ngaoundéré",
    "id": "node/4453234586"
  },
  "geometry": {
    "type": "Point",
    "coordinates": [
      13.5961226,
      7.3100248
    ]
  }
}
]
}
