{
"type": "FeatureCollection",
"features": [
{
  "type": "Feature",
  "id": "node/2755607675",
  "properties": {
    "amenity": "hospital",
    "gns:ufi": "-2131517",
    "name": "Firestone Medical Center",
    "source": "GNS;Personal knowledge",
    "id": "node/2755607675"
  },
  "geometry": {
    "type": "Point",
    "coordinates": [
      -10.4694925,
      6.3531195
    ]
  }
},
{
  "type": "Feature",
  "id": "node/3198032311",
  "properties": {
    "accuracy": "British Red Cross - GPS",
    "amenity": "hospital",
    "capacity:beds": "31",
    "capacity:beds:planned": "31",
    "check_date": "2014-11-17T00:00:00",
    "disease:ebola": "yes",
    "health_facility:id": "ETU_LBR_005",
    "health_facility:type": "field_hospital",
    "is_in": "Harbel City",
    "is_in:county": "Margibi",
    "is_in:district": "Firestone",
    "name": "Margibi (Firestone) ETU",
    "operational_status": "open",
    "operator": "Firestone",
    "source": "UNMEER ; https://data.hdx.rwlabs.org/dataset/ebola-treatment-centers",
    "start_date": "2014-11-16T00:00:00",
    "id": "node/3198032311"
  },
  "geometry": {
    "type": "Point",
    "coordinates": [
      -10.47,
      6.353
    ]
  }
}
]
}
