{
"type": "FeatureCollection",
"features": [
{
  "type": "Feature",
  "id": "node/1309028041",
  "properties": {
    "amenity": "hospital",
    "name": "Centre Hospitalier Régional de San Pédro",
    "id": "node/1309028041"
  },
  "geometry": {
    "type": "Point",
    "coordinates": [
      -6.6362977,
      4.7466375
    ]
  }
},
{
  "type": "Feature",
  "id": "node/4806184022",
  "properties": {
    "amenity": "hospital",
    "name": "Maternité Municipale Déléguée Henriette Konan Bédié du Bardot",
    "name:fr": "Maternité Municipale Déléguée Henriette Konan Bédié du Bardot",
    "id": "node/4806184022"
  },
  "geometry": {
    "type": "Point",
    "coordinates": [
      -6.6517799,
      4.7783024
    ]
  }
}
]
}
